LICENSE.txt
MANIFEST.in
README.md
setup.py
nyc_geoclient/__init__.py
nyc_geoclient/api.py
nyc_geoclient/version.py
nyc_geoclient.egg-info/PKG-INFO
nyc_geoclient.egg-info/SOURCES.txt
nyc_geoclient.egg-info/dependency_links.txt
nyc_geoclient.egg-info/requires.txt
nyc_geoclient.egg-info/top_level.txt