Metadata-Version: 1.0
Name: nyc-geoclient
Version: 0.0.1
Summary: Python bindings for the NYC Geoclient REST API
Home-page: http://github.com/talos/nyc-geoclient
Author: John Krauss
Author-email: john@accursedware.com
License: BSD
Platform: UNKNOWN
Classifier: Development Status :: 3 - Alpha
Classifier: Intended Audience :: Developers
Classifier: Topic :: Software Development
Classifier: Natural Language :: English
Classifier: License :: OSI Approved :: BSD License
Classifier: Programming Language :: Python :: 2.6
Classifier: Programming Language :: Python :: 2.7
